.pypyreadme
MANIFEST.in
README.md
VERSION
setup.cfg
setup.py
bin/ps1
src/ps1.egg-info/PKG-INFO
src/ps1.egg-info/SOURCES.txt
src/ps1.egg-info/dependency_links.txt
src/ps1.egg-info/requires.txt
src/ps1.egg-info/top_level.txt
src/ps1api/__init__.py
src/ps1api/examples/dark/entropy.sh
src/ps1api/examples/dark/face.sh
src/ps1api/examples/dark/filecount.sh
src/ps1api/examples/dark/greenguy.sh
src/ps1api/examples/dark/ips.sh
src/ps1api/examples/dark/nightrider.sh
src/ps1api/examples/dark/no_unicode.sh
src/ps1api/examples/dark/parrot.sh
src/ps1api/examples/dark/plainjane.sh
src/ps1api/examples/dark/purplegoblin.sh
src/ps1api/examples/dark/skulls.sh
src/ps1api/examples/dark/stev0_work.sh
src/ps1api/examples/dark/too_many_options.sh
src/ps1api/examples/light/fire_ice.sh
src/ps1api/examples/light/magenta.sh
src/ps1api/examples/light/powderpuff.sh