Metadata-Version: 2.1
Name: ps1
Version: 0.0.13
Summary: This package allows you to easily customize your PS1 bash prompt
Home-page: https://github.com/shollingsworth/ps1
Author: Steven Hollingsworth
Author-email: hollingsworth.stevend@gmail.com
License: MIT
Project-URL: Changes, https://github.com/shollingsworth/ps1/blob/main/CHANGELOG.md
Project-URL: Source Code, https://github.com/shollingsworth/ps1
Project-URL: Issue Tracker, https://github.com/shollingsworth/ps1/issues/
Project-URL: Twitter, https://twitter.com/_stevo
Project-URL: Documentation, https://shollingsworth.github.io/ps1/index.html
Keywords: bash,PS1,terminal
Platform: UNKNOWN
Classifier: Development Status :: 5 - Production/Stable
Classifier: Environment :: Console
Classifier: Intended Audience :: Developers
Classifier: License :: OSI Approved :: MIT License
Classifier: Intended Audience :: End Users/Desktop
Classifier: Intended Audience :: Information Technology
Classifier: Operating System :: OS Independent
Classifier: Programming Language :: Python :: 3 :: Only
Classifier: Programming Language :: Python :: 3.6
Classifier: Programming Language :: Python :: 3.7
Classifier: Programming Language :: Python :: 3.8
Classifier: Programming Language :: Python :: 3.9
Classifier: Topic :: Documentation
Classifier: Topic :: Text Editors :: Documentation
Requires-Python: >=3.6
